discord_music_streamer/__init__.py
discord_music_streamer/commands.py
discord_music_streamer/music_player.py
discord_music_streamer/queue_manager.py
discord_music_streamer/youtube_extractor.py
discord_music_streamer/youtube_source.py
discord_music_streamer-0.1.1.dist-info/licenses/LICENSE
discord_music_streamer-0.1.1.dist-info/METADATA
discord_music_streamer-0.1.1.dist-info/WHEEL
discord_music_streamer-0.1.1.dist-info/top_level.txt
discord_music_streamer-0.1.1.dist-info/RECORD
