Metadata-Version: 2.4
Name: discord-music-streamer
Version: 0.1.1
Summary: A Python library for streaming music in Discord voice channels with YouTube support
Home-page: https://github.com/yourusername/discord-music-streamer
Author: Your Name
Author-email: Your Name <you@example.com>
Project-URL: Homepage, https://github.com/yourusername/discord-music-streamer
Project-URL: Repository, https://github.com/yourusername/discord-music-streamer
Project-URL: Issues, https://github.com/yourusername/discord-music-streamer/issues
Classifier: Development Status :: 3 - Alpha
Classifier: Intended Audience :: Developers
Classifier: License :: OSI Approved :: MIT License
Classifier: Programming Language :: Python :: 3
Classifier: Programming Language :: Python :: 3.8
Classifier: Programming Language :: Python :: 3.9
Classifier: Programming Language :: Python :: 3.10
Classifier: Programming Language :: Python :: 3.11
Requires-Python: >=3.8
License-File: LICENSE
Requires-Dist: discord.py[voice]>=2.0.0
Requires-Dist: aiohttp>=3.8.0
Requires-Dist: PyNaCl>=1.5.0
Requires-Dist: asyncio
Requires-Dist: setuptools>=75.3.2
Requires-Dist: build>=1.2.2.post1
Requires-Dist: twine>=6.1.0
Dynamic: author
Dynamic: home-page
Dynamic: license-file
Dynamic: requires-python
